{
  "data": "dataset/df_preprocessed.csv",
  "bundle": "output/final_gmr_recommender_bundle.joblib",
  "gmr_grid": [
    0.0,
    0.05,
    0.1,
    0.15,
    0.2,
    0.25,
    0.3,
    0.35,
    0.4,
    0.45,
    0.5,
    0.55,
    0.6
  ],
  "thresholds": [
    0.6,
    0.7,
    0.8,
    0.9
  ],
  "max_gmr_change": null,
  "max_price_increase_pct": null,
  "max_price_gap_min_pct": null,
  "model_name": "HistGradientBoostingClassifier",
  "model_config": "initial",
  "features": [
    "product_model",
    "kw",
    "unit_price",
    "qty",
    "subtotal_price",
    "gross_margin_rate",
    "energy_grant_amount",
    "competitor_a",
    "competitor_b",
    "competitor_c",
    "is_compe_a",
    "is_compe_b",
    "is_compe_c",
    "competitor_count_available",
    "avg_competitor_price",
    "min_competitor_price",
    "max_competitor_price",
    "price_gap_avg_competitor",
    "price_gap_avg_competitor_pct",
    "price_gap_min_competitor",
    "price_gap_min_competitor_pct",
    "higher_than_avg_competitor",
    "is_lower_than_competitor",
    "effective_price_after_grant",
    "grant_ratio_to_subtotal",
    "estimated_cost",
    "estimated_gross_profit"
  ]
}